ez_ai/__init__.py
ethan_super_ai_wrapper-0.1.16.dist-info/METADATA
ethan_super_ai_wrapper-0.1.16.dist-info/WHEEL
ethan_super_ai_wrapper-0.1.16.dist-info/top_level.txt
ethan_super_ai_wrapper-0.1.16.dist-info/RECORD
