Metadata-Version: 2.1
Name: ethan-super-ai-wrapper
Version: 0.1.16
Summary: The easiest AI wrapper for OpenAI, Anthropic, Gemini, and HuggingFace
Author: Ethan
Requires-Dist: requests
Requires-Dist: huggingface-hub
